financial_engine/__init__.py
financial_engine/calculations/__init__.py
financial_engine/calculations/ratios.py
financial_engine/constants/__init__.py
financial_engine/constants/constants.py
financial_engine/core/__init__.py
financial_engine/core/engine.py
financial_engine/database/__init__.py
financial_engine/database/mongo.py
financial_engine/database/s3.py
financial_engine/utilities/__init__.py
financial_engine/utilities/cacher.py
financial_engine/utilities/parser.py
financial_engine-0.1.4.dist-info/licenses/LICENSE
financial_engine-0.1.4.dist-info/METADATA
financial_engine-0.1.4.dist-info/WHEEL
financial_engine-0.1.4.dist-info/top_level.txt
financial_engine-0.1.4.dist-info/RECORD
