Metadata-Version: 2.4
Name: financial_engine
Version: 0.1.4
Summary: A time-machine style financial backtesting and ratio analysis engine
Author-email: Raj Adhikari <adhikarirajj07@gmail.com>
Maintainer-email: Numair Sayed <sayednumair2019@gmail.com>
License: Proprietary
Requires-Python: >=3.10
License-File: LICENSE
Requires-Dist: pandas
Requires-Dist: python-dotenv
Requires-Dist: aioboto3
Requires-Dist: motor
Requires-Dist: boto3
Requires-Dist: pyarrow
Dynamic: license-file
